chipshot/__init__.py
chipshot/__main__.py
chipshot/cli.py
chipshot/compare.py
chipshot/config.py
chipshot/exceptions.py
chipshot/logger.py
chipshot/py.typed
chipshot/reader/__init__.py
chipshot/reader/encoding.py
chipshot/reader/header.py
chipshot/reader/identity.py
chipshot/reader/newlines.py
chipshot/reader/prologue.py
chipshot/render.py
chipshot/resources/__init__.py
chipshot/resources/default-config.toml
chipshot/shared.py
chipshot/writer.py
chipshot-0.8.0.dist-info/LICENSE.txt
chipshot-0.8.0.dist-info/METADATA
chipshot-0.8.0.dist-info/WHEEL
chipshot-0.8.0.dist-info/entry_points.txt
chipshot-0.8.0.dist-info/RECORD
