Metadata-Version: 2.3
Name: chipshot
Version: 0.8.0
Summary: Set up game-winning headers!
License: MIT
Author: Kurt McKee
Author-email: contactme@kurtmckee.org
Requires-Python: >=3.9
Classifier: License :: OSI Approved :: MIT License
Classifier: Programming Language :: Python :: 3
Classifier: Programming Language :: Python :: 3.9
Classifier: Programming Language :: Python :: 3.10
Classifier: Programming Language :: Python :: 3.11
Classifier: Programming Language :: Python :: 3.12
Classifier: Programming Language :: Python :: 3.13
Requires-Dist: click (>=8.1.7)
Requires-Dist: jinja2 (>=3.1.3)
Requires-Dist: tomli (>=2.0.1) ; python_version < "3.11"
